Workbook

Sheet Row Data
A1: Supply Chain Raw Data
A2: Product type | B2: SKU | C2: Price | D2: Availability | E2: Number of products sold | F2: Revenue generated | G2: Customer demographics | H2: Stock levels | I2: Lead times | J2: Order quantities | K2: Shipping times | L2: Shipping carriers | M2: Shipping costs | N2: Supplier name | O2: Location | P2: Lead time | Q2: Production volumes | R2: Manufacturing lead time | S2: Manufacturing costs | T2: Inspection results | U2: Defect rates | V2: Transportation modes | W2: Routes | X2: Costs
A3: haircare | B3: SKU0 | C3: 69.808006 | D3: 55 | E3: 802 | F3: 8661.9968 | G3: Non-binary | H3: 58 | I3: 7 | J3: 96 | K3: 4 | L3: Carrier B | M3: 2.9565721 | N3: Supplier 3 | O3: Mumbai | P3: 29 | Q3: 215 | R3: 29 | S3: 46.279879 | T3: Pending | U3: 0.22641036 | V3: Road | W3: Route B | X3: 187.75208
A4: skincare | B4: SKU1 | C4: 14.843523 | D4: 95 | E4: 736 | F4: 7460.9001 | G4: Female | H4: 53 | I4: 30 | J4: 37 | K4: 2 | L4: Carrier A | M4: 9.7165748 | N4: Supplier 3 | O4: Mumbai | P4: 23 | Q4: 517 | R4: 30 | S4: 33.616769 | T4: Pending | U4: 4.854068 | V4: Road | W4: Route B | X4: 503.06558
A5: haircare | B5: SKU2 | C5: 11.319683 | D5: 34 | E5: 8 | F5: 9577.7496 | G5: Unknown | H5: 1 | I5: 10 | J5: 88 | K5: 2 | L5: Carrier B | M5: 8.0544793 | N5: Supplier 1 | O5: Mumbai | P5: 12 | Q5: 971 | R5: 27 | S5: 30.688019 | T5: Pending | U5: 4.5805926 | V5: Air | W5: Route C | X5: 141.92028
A6: skincare | B6: SKU3 | C6: 61.163343 | D6: 68 | E6: 83 | F6: 7766.8364 | G6: Non-binary | H6: 23 | I6: 13 | J6: 59 | K6: 6 | L6: Carrier C | M6: 1.7295686 | N6: Supplier 5 | O6: Kolkata | P6: 24 | Q6: 937 | R6: 18 | S6: 35.624741 | T6: Fail | U6: 4.7466486 | V6: Rail | W6: Route A | X6: 254.77616
A7: skincare | B7: SKU4 | C7: 4.805496 | D7: 26 | E7: 871 | F7: 2686.5052 | G7: Non-binary | H7: 5 | I7: 3 | J7: 56 | K7: 8 | L7: Carrier A | M7: 3.8905479 | N7: Supplier 1 | O7: Delhi | P7: 5 | Q7: 414 | R7: 3 | S7: 92.065161 | T7: Fail | U7: 3.1455795 | V7: Air | W7: Route A | X7: 923.44063
A8: haircare | B8: SKU5 | C8: 1.699976 | D8: 87 | E8: 147 | F8: 2828.3487 | G8: Non-binary | H8: 90 | I8: 27 | J8: 66 | K8: 3 | L8: Carrier B | M8: 4.4440989 | N8: Supplier 4 | O8: Bangalore | P8: 10 | Q8: 104 | R8: 17 | S8: 56.766476 | T8: Fail | U8: 2.7791935 | V8: Road | W8: Route A | X8: 235.46124
A9: skincare | B9: SKU6 | C9: 4.0783329 | D9: 48 | E9: 65 | F9: 7823.4766 | G9: Male | H9: 11 | I9: 15 | J9: 58 | K9: 8 | L9: Carrier C | M9: 3.8807633 | N9: Supplier 3 | O9: Kolkata | P9: 14 | Q9: 314 | R9: 24 | S9: 1.0850686 | T9: Pending | U9: 1.0009106 | V9: Sea | W9: Route A | X9: 134.3691
A10: cosmetics | B10: SKU7 | C10: 42.958384 | D10: 59 | E10: 426 | F10: 8496.1038 | G10: Female | H10: 93 | I10: 17 | J10: 11 | K10: 1 | L10: Carrier B | M10: 2.3483388 | N10: Supplier 4 | O10: Bangalore | P10: 22 | Q10: 564 | R10: 1 | S10: 99.466109 | T10: Fail | U10: 0.39817719 | V10: Road | W10: Route C | X10: 802.05631
A11: cosmetics | B11: SKU8 | C11: 68.717597 | D11: 78 | E11: 150 | F11: 7517.3632 | G11: Female | H11: 5 | I11: 10 | J11: 15 | K11: 7 | L11: Carrier C | M11: 3.4047339 | N11: Supplier 4 | O11: Mumbai | P11: 13 | Q11: 769 | R11: 8 | S11: 11.423027 | T11: Pending | U11: 2.7098627 | V11: Sea | W11: Route B | X11: 505.55713
A12: skincare | B12: SKU9 | C12: 64.015733 | D12: 35 | E12: 980 | F12: 4971.146 | G12: Unknown | H12: 14 | I12: 27 | J12: 83 | K12: 1 | L12: Carrier A | M12: 7.1666453 | N12: Supplier 2 | O12: Chennai | P12: 29 | Q12: 963 | R12: 23 | S12: 47.957602 | T12: Pending | U12: 3.8446145 | V12: Rail | W12: Route B | X12: 995.92946
A13: skincare | B13: SKU10 | C13: 15.707796 | D13: 11 | E13: 996 | F13: 2330.9658 | G13: Non-binary | H13: 51 | I13: 13 | J13: 80 | K13: 2 | L13: Carrier C | M13: 8.6732112 | N13: Supplier 5 | O13: Kolkata | P13: 18 | Q13: 830 | R13: 5 | S13: 96.527353 | T13: Pass | U13: 1.7273139 | V13: Road | W13: Route B | X13: 806.10318
A14: skincare | B14: SKU11 | C14: 90.63546 | D14: 95 | E14: 960 | F14: 6099.9441 | G14: Female | H14: 46 | I14: 23 | J14: 60 | K14: 1 | L14: Carrier A | M14: 4.5239431 | N14: Supplier 2 | O14: Kolkata | P14: 28 | Q14: 362 | R14: 11 | S14: 27.592363 | T14: Pending | U14: 0.021169821 | V14: Air | W14: Route A | X14: 126.72303
... A102: haircare | B102: SKU99 | C102: 68.517833 | D102: 17 | E102: 627 | F102: 9185.1858 | G102: Unknown | H102: 55 | I102: 8 | J102: 59 | K102: 6 | L102: Carrier B | M102: 1.3110238 | N102: Supplier 2 | O102: Chennai | P102: 29 | Q102: 921 | R102: 2 | S102: 38.072899 | T102: Fail | U102: 0.34602729 | V102: Rail | W102: Route B | X102: 210.74301

Sheet Analysis
A2: Summary Statistics
A3: Metric | B3: Summary
A4: Total Revenue | B4: =SUM(Tbl_sales[Revenue generated]) -> 577604.82
A5: Total unit Sold | B5: =SUM(Tbl_sales[Number of products sold]) -> 46099
A6: Average Defeact Rate | B6: =AVERAGE(Tbl_sales[Defect rates]) -> 2.277158
A7: Average Lead time | B7: =AVERAGE(Tbl_sales[Lead times]) -> 15.96
A8: Low Stock Item | B8: =COUNTIF(Tbl_sales[Stock levels],"<=10") -> 17
A11: REVENUE BY PRODUCT TYPE
A12: Product Type | B12: Total Revenue | C12: Units Sold | D12: Avg Price
A13: {=_xlfn.UNIQUE(Tbl_sales[Product type])} -> haircare | B13: =IF(A13<>"",SUMIF(Tbl_sales[Product type],A13,Tbl_sales[Revenue generated]),"") -> 174455.39 | C13: =IF(A13<>"",SUMIF(Tbl_sales[Product type],A13,Tbl_sales[Number of products sold]),"") -> 13611 | D13: =IF(A13<>"",AVERAGEIF(Tbl_sales[Product type],A13,Tbl_sales[Price]),"") -> 46.014279
A14: skincare | B14: =IF(A14<>"",SUMIF(Tbl_sales[Product type],A14,Tbl_sales[Revenue generated]),"") -> 241628.16 | C14: =IF(A14<>"",SUMIF(Tbl_sales[Product type],A14,Tbl_sales[Number of products sold]),"") -> 20731 | D14: =AVERAGEIF(Tbl_sales[Product type],A14,Tbl_sales[Price]) -> 47.259329
A15: cosmetics | B15: =IF(A15<>"",SUMIF(Tbl_sales[Product type],A15,Tbl_sales[Revenue generated]),"") -> 161521.27 | C15: =IF(A15<>"",SUMIF(Tbl_sales[Product type],A15,Tbl_sales[Number of products sold]),"") -> 11757 | D15: =AVERAGEIF(Tbl_sales[Product type],A15,Tbl_sales[Price]) -> 57.361058
A20: SUPPLIER QUALITY ANALYSIS
A21: Supplier name | B21: Avg Defect Rate | C21: Avg Lead Time | D21: Avg Manufacturing Lead Time | E21: Avg Manufacturing Cost
A22: {=_xlfn._xlws.SORT(_xlfn.UNIQUE(Tbl_sales[Supplier name],FALSE,FALSE))} -> Supplier 1 | B22: =IF(A22<>"",AVERAGEIF(Tbl_sales[Supplier name],A22,Tbl_sales[Defect rates]),"") -> 1.8036297 | C22: =IF(A22<>"",AVERAGEIF(Tbl_sales[Supplier name],A22,Tbl_sales[Lead time]),"") -> 14.777778 | D22: =IF(A22<>"",AVERAGEIF(Tbl_sales[Supplier name],A22,Tbl_sales[Manufacturing lead time]),"") -> 12.592593 | E22: =IF(A22<>"",AVERAGEIF(Tbl_sales[Supplier name],A22,Tbl_sales[Costs]),"") -> 574.85114
A23: Supplier 2 | B23: =IF(A23<>"",AVERAGEIF(Tbl_sales[Supplier name],A23,Tbl_sales[Defect rates]),"") -> 2.3627501 | C23: =IF(A23<>"",AVERAGEIF(Tbl_sales[Supplier name],A23,Tbl_sales[Lead time]),"") -> 18.545455 | D23: =IF(A23<>"",AVERAGEIF(Tbl_sales[Supplier name],A23,Tbl_sales[Manufacturing lead time]),"") -> 15.590909 | E23: =IF(A23<>"",AVERAGEIF(Tbl_sales[Supplier name],A23,Tbl_sales[Costs]),"") -> 515.02724
A24: Supplier 3 | B24: =IF(A24<>"",AVERAGEIF(Tbl_sales[Supplier name],A24,Tbl_sales[Defect rates]),"") -> 2.465786 | C24: =IF(A24<>"",AVERAGEIF(Tbl_sales[Supplier name],A24,Tbl_sales[Lead time]),"") -> 20.133333 | D24: =IF(A24<>"",AVERAGEIF(Tbl_sales[Supplier name],A24,Tbl_sales[Manufacturing lead time]),"") -> 14.933333 | E24: =IF(A24<>"",AVERAGEIF(Tbl_sales[Supplier name],A24,Tbl_sales[Costs]),"") -> 468.8001
A25: Supplier 4 | B25: =IF(A25<>"",AVERAGEIF(Tbl_sales[Supplier name],A25,Tbl_sales[Defect rates]),"") -> 2.3373974 | C25: =IF(A25<>"",AVERAGEIF(Tbl_sales[Supplier name],A25,Tbl_sales[Lead time]),"") -> 15.222222 | D25: =IF(A25<>"",AVERAGEIF(Tbl_sales[Supplier name],A25,Tbl_sales[Manufacturing lead time]),"") -> 15.333333 | E25: =IF(A25<>"",AVERAGEIF(Tbl_sales[Supplier name],A25,Tbl_sales[Costs]),"") -> 521.81042
A26: Supplier 5 | B26: =IF(A26<>"",AVERAGEIF(Tbl_sales[Supplier name],A26,Tbl_sales[Defect rates]),"") -> 2.6654083 | C26: =IF(A26<>"",AVERAGEIF(Tbl_sales[Supplier name],A26,Tbl_sales[Lead time]),"") -> 18.055556 | D26: =IF(A26<>"",AVERAGEIF(Tbl_sales[Supplier name],A26,Tbl_sales[Manufacturing lead time]),"") -> 16.333333 | E26: =IF(A26<>"",AVERAGEIF(Tbl_sales[Supplier name],A26,Tbl_sales[Costs]),"") -> 536.02273
A29: Shipping Efficiency Analysis
A30: Shipping Carrier | B30: Avg Shipping Time | C30: Avg Shipping Cost
A31: {=_xlfn.UNIQUE(Tbl_sales[Shipping carriers],FALSE)} -> Carrier B | B31: =IF(A31<>"",AVERAGEIF(Tbl_sales[Shipping carriers],A31,Tbl_sales[Shipping times]),"") -> 5.3023256 | C31: =IF(A31<>"",AVERAGEIF(Tbl_sales[Shipping carriers],A31,Tbl_sales[Shipping costs]),"") -> 5.509247
A32: Carrier A | B32: =IF(A32<>"",AVERAGEIF(Tbl_sales[Shipping carriers],A32,Tbl_sales[Shipping times]),"") -> 6.1428571 | C32: =IF(A32<>"",AVERAGEIF(Tbl_sales[Shipping carriers],A32,Tbl_sales[Shipping costs]),"") -> 5.5549225
A33: Carrier C | B33: =IF(A33<>"",AVERAGEIF(Tbl_sales[Shipping carriers],A33,Tbl_sales[Shipping times]),"") -> 6.0344828 | C33: =IF(A33<>"",AVERAGEIF(Tbl_sales[Shipping carriers],A33,Tbl_sales[Shipping costs]),"") -> 5.5992916
A36: STOCK RISK ANALYSIS | F36: =COUNTIF(F37:F137,"=Reorder") -> 17
A37: SKU | B37: Availability | C37: Stock levels | D37: Lead times | E37: Shipping times | F37: Status
A38: SKU0 | B38: =_xlfn.XLOOKUP(A38,Tbl_sales[SKU],Tbl_sales[Availability]) -> 55 | C38: =_xlfn.XLOOKUP(A38,Tbl_sales[SKU],Tbl_sales[Stock levels]) -> 58 | D38: =_xlfn.XLOOKUP(A38,Tbl_sales[SKU],Tbl_sales[Lead times]) -> 7 | E38: =_xlfn.XLOOKUP(A38,Tbl_sales[SKU],Tbl_sales[Shipping times]) -> 4 | F38: =IF(C38<=10,"Reorder","OK") -> OK
A39: SKU1 | B39: =_xlfn.XLOOKUP(A39,Tbl_sales[SKU],Tbl_sales[Availability]) -> 95 | C39: =_xlfn.XLOOKUP(A39,Tbl_sales[SKU],Tbl_sales[Stock levels]) -> 53 | D39: =_xlfn.XLOOKUP(A39,Tbl_sales[SKU],Tbl_sales[Lead times]) -> 30 | E39: =_xlfn.XLOOKUP(A39,Tbl_sales[SKU],Tbl_sales[Shipping times]) -> 2 | F39: =IF(C39<=10,"Reorder","OK") -> OK
A40: SKU2 | B40: =_xlfn.XLOOKUP(A40,Tbl_sales[SKU],Tbl_sales[Availability]) -> 34 | C40: =_xlfn.XLOOKUP(A40,Tbl_sales[SKU],Tbl_sales[Stock levels]) -> 1 | D40: =_xlfn.XLOOKUP(A40,Tbl_sales[SKU],Tbl_sales[Lead times]) -> 10 | E40: =_xlfn.XLOOKUP(A40,Tbl_sales[SKU],Tbl_sales[Shipping times]) -> 2 | F40: =IF(C40<=10,"Reorder","OK") -> Reorder
A41: SKU3 | B41: =_xlfn.XLOOKUP(A41,Tbl_sales[SKU],Tbl_sales[Availability]) -> 68 | C41: =_xlfn.XLOOKUP(A41,Tbl_sales[SKU],Tbl_sales[Stock levels]) -> 23 | D41: =_xlfn.XLOOKUP(A41,Tbl_sales[SKU],Tbl_sales[Lead times]) -> 13 | E41: =_xlfn.XLOOKUP(A41,Tbl_sales[SKU],Tbl_sales[Shipping times]) -> 6 | F41: =IF(C41<=10,"Reorder","OK") -> OK
A42: SKU4 | B42: =_xlfn.XLOOKUP(A42,Tbl_sales[SKU],Tbl_sales[Availability]) -> 26 | C42: =_xlfn.XLOOKUP(A42,Tbl_sales[SKU],Tbl_sales[Stock levels]) -> 5 | D42: =_xlfn.XLOOKUP(A42,Tbl_sales[SKU],Tbl_sales[Lead times]) -> 3 | E42: =_xlfn.XLOOKUP(A42,Tbl_sales[SKU],Tbl_sales[Shipping times]) -> 8 | F42: =IF(C42<=10,"Reorder","OK") -> Reorder
A43: SKU5 | B43: =_xlfn.XLOOKUP(A43,Tbl_sales[SKU],Tbl_sales[Availability]) -> 87 | C43: =_xlfn.XLOOKUP(A43,Tbl_sales[SKU],Tbl_sales[Stock levels]) -> 90 | D43: =_xlfn.XLOOKUP(A43,Tbl_sales[SKU],Tbl_sales[Lead times]) -> 27 | E43: =_xlfn.XLOOKUP(A43,Tbl_sales[SKU],Tbl_sales[Shipping times]) -> 3 | F43: =IF(C43<=10,"Reorder","OK") -> OK
A44: SKU6 | B44: =_xlfn.XLOOKUP(A44,Tbl_sales[SKU],Tbl_sales[Availability]) -> 48 | C44: =_xlfn.XLOOKUP(A44,Tbl_sales[SKU],Tbl_sales[Stock levels]) -> 11 | D44: =_xlfn.XLOOKUP(A44,Tbl_sales[SKU],Tbl_sales[Lead times]) -> 15 | E44: =_xlfn.XLOOKUP(A44,Tbl_sales[SKU],Tbl_sales[Shipping times]) -> 8 | F44: =IF(C44<=10,"Reorder","OK") -> OK
A45: SKU7 | B45: =_xlfn.XLOOKUP(A45,Tbl_sales[SKU],Tbl_sales[Availability]) -> 59 | C45: =_xlfn.XLOOKUP(A45,Tbl_sales[SKU],Tbl_sales[Stock levels]) -> 93 | D45: =_xlfn.XLOOKUP(A45,Tbl_sales[SKU],Tbl_sales[Lead times]) -> 17 | E45: =_xlfn.XLOOKUP(A45,Tbl_sales[SKU],Tbl_sales[Shipping times]) -> 1 | F45: =IF(C45<=10,"Reorder","OK") -> OK
A46: SKU8 | B46: =_xlfn.XLOOKUP(A46,Tbl_sales[SKU],Tbl_sales[Availability]) -> 78 | C46: =_xlfn.XLOOKUP(A46,Tbl_sales[SKU],Tbl_sales[Stock levels]) -> 5 | D46: =_xlfn.XLOOKUP(A46,Tbl_sales[SKU],Tbl_sales[Lead times]) -> 10 | E46: =_xlfn.XLOOKUP(A46,Tbl_sales[SKU],Tbl_sales[Shipping times]) -> 7 | F46: =IF(C46<=10,"Reorder","OK") -> Reorder
A47: SKU9 | B47: =_xlfn.XLOOKUP(A47,Tbl_sales[SKU],Tbl_sales[Availability]) -> 35 | C47: =_xlfn.XLOOKUP(A47,Tbl_sales[SKU],Tbl_sales[Stock levels]) -> 14 | D47: =_xlfn.XLOOKUP(A47,Tbl_sales[SKU],Tbl_sales[Lead times]) -> 27 | E47: =_xlfn.XLOOKUP(A47,Tbl_sales[SKU],Tbl_sales[Shipping times]) -> 1 | F47: =IF(C47<=10,"Reorder","OK") -> OK
A48: SKU10 | B48: =_xlfn.XLOOKUP(A48,Tbl_sales[SKU],Tbl_sales[Availability]) -> 11 | C48: =_xlfn.XLOOKUP(A48,Tbl_sales[SKU],Tbl_sales[Stock levels]) -> 51 | D48: =_xlfn.XLOOKUP(A48,Tbl_sales[SKU],Tbl_sales[Lead times]) -> 13 | E48: =_xlfn.XLOOKUP(A48,Tbl_sales[SKU],Tbl_sales[Shipping times]) -> 2 | F48: =IF(C48<=10,"Reorder","OK") -> OK
A49: SKU11 | B49: =_xlfn.XLOOKUP(A49,Tbl_sales[SKU],Tbl_sales[Availability]) -> 95 | C49: =_xlfn.XLOOKUP(A49,Tbl_sales[SKU],Tbl_sales[Stock levels]) -> 46 | D49: =_xlfn.XLOOKUP(A49,Tbl_sales[SKU],Tbl_sales[Lead times]) -> 23 | E49: =_xlfn.XLOOKUP(A49,Tbl_sales[SKU],Tbl_sales[Shipping times]) -> 1 | F49: =IF(C49<=10,"Reorder","OK") -> OK
... A137: SKU99 | B137: =_xlfn.XLOOKUP(A137,Tbl_sales[SKU],Tbl_sales[Availability]) -> 17 | C137: =_xlfn.XLOOKUP(A137,Tbl_sales[SKU],Tbl_sales[Stock levels]) -> 55 | D137: =_xlfn.XLOOKUP(A137,Tbl_sales[SKU],Tbl_sales[Lead times]) -> 8 | E137: =_xlfn.XLOOKUP(A137,Tbl_sales[SKU],Tbl_sales[Shipping times]) -> 6 | F137: =IF(C137<=10,"Reorder","OK") -> OK

Sheet Dashboard
B1: Supply Chain Performance Dashboard
B11: REVENUE BY PRODUCT TYPE | I11: STOCK ALERTS — ITEMS NEEDING REORDER
B12: Product Type | C12: Total Revenue | D12: Units Sold | E12: Avg Price | I12: SKU | J12: Availability | K12: Stock levels | L12: Lead times | M12: Status
B13: =Analysis!A13 -> haircare | C13: =Analysis!B13 -> 174455.39 | D13: =Analysis!C13 -> 13611 | E13: =Analysis!D13 -> 46.014279 | I13: {=_xlfn._xlws.FILTER(Analysis!A37:D137,Analysis!F37:F137="Reorder")} -> SKU2 | J13: 34 | K13: 1 | L13: 10 | M13: =IF(I13<>"","REORDER NOW","") -> REORDER NOW
B14: =Analysis!A14 -> skincare | C14: =Analysis!B14 -> 241628.16 | D14: =Analysis!C14 -> 20731 | E14: =Analysis!D14 -> 47.259329 | I14: SKU4 | J14: 26 | K14: 5 | L14: 3 | M14: =IF(I14<>"","REORDER NOW","") -> REORDER NOW
B15: =Analysis!A15 -> cosmetics | C15: =Analysis!B15 -> 161521.27 | D15: =Analysis!C15 -> 11757 | E15: =Analysis!D15 -> 57.361058 | I15: SKU8 | J15: 78 | K15: 5 | L15: 10 | M15: =IF(I15<>"","REORDER NOW","") -> REORDER NOW
I16: SKU15 | J16: 94 | K16: 9 | L16: 8 | M16: =IF(I16<>"","REORDER NOW","") -> REORDER NOW
B17: SUPPLIER QUALITY (Best → Worst) | I17: SKU16 | J17: 74 | K17: 2 | L17: 5 | M17: =IF(I17<>"","REORDER NOW","") -> REORDER NOW
B18: =Analysis!A21 -> Supplier name | C18: =Analysis!B21 -> Avg Defect Rate | D18: =Analysis!C21 -> Avg Lead Time | E18: =Analysis!D21 -> Avg Manufacturing Lead Time | F18: =Analysis!E21 -> Avg Manufacturing Cost | G18: Status | I18: SKU18 | J18: 23 | K18: 10 | L18: 10 | M18: =IF(I18<>"","REORDER NOW","") -> REORDER NOW
B19: =Analysis!A22 -> Supplier 1 | C19: =Analysis!B22 -> 1.8036297 | D19: =Analysis!C22 -> 14.777778 | E19: =Analysis!D22 -> 12.592593 | F19: =Analysis!E22 -> 574.85114 | G19: =IF(C19<2,"Best",IF(C19<=2.5,"Good","Average")) -> Best | I19: SKU24 | J19: 32 | K19: 4 | L19: 26 | M19: =IF(I19<>"","REORDER NOW","") -> REORDER NOW
B20: =Analysis!A23 -> Supplier 2 | C20: =Analysis!B23 -> 2.3627501 | D20: =Analysis!C23 -> 18.545455 | E20: =Analysis!D23 -> 15.590909 | F20: =Analysis!E23 -> 515.02724 | G20: =IF(C20<2,"Best",IF(C20<=2.5,"Good","Average")) -> Good | I20: SKU31 | J20: 28 | K20: 6 | L20: 17 | M20: =IF(I20<>"","REORDER NOW","") -> REORDER NOW
B21: =Analysis!A24 -> Supplier 3 | C21: =Analysis!B24 -> 2.465786 | D21: =Analysis!C24 -> 20.133333 | E21: =Analysis!D24 -> 14.933333 | F21: =Analysis!E24 -> 468.8001 | G21: =IF(C21<2,"Best",IF(C21<=2.5,"Good","Average")) -> Good | I21: SKU33 | J21: 63 | K21: 4 | L21: 17 | M21: =IF(I21<>"","REORDER NOW","") -> REORDER NOW
B22: =Analysis!A25 -> Supplier 4 | C22: =Analysis!B25 -> 2.3373974 | D22: =Analysis!C25 -> 15.222222 | E22: =Analysis!D25 -> 15.333333 | F22: =Analysis!E25 -> 521.81042 | G22: =IF(C22<2,"Best",IF(C22<=2.5,"Good","Average")) -> Good | I22: SKU34 | J22: 96 | K22: 1 | L22: 26 | M22: =IF(I22<>"","REORDER NOW","") -> REORDER NOW
B23: =Analysis!A26 -> Supplier 5 | C23: =Analysis!B26 -> 2.6654083 | D23: =Analysis!C26 -> 18.055556 | E23: =Analysis!D26 -> 16.333333 | F23: =Analysis!E26 -> 536.02273 | G23: =IF(C23<2,"Best",IF(C23<=2.5,"Good","Average")) -> Average | I23: SKU47 | J23: 93 | K23: 4 | L23: 15 | M23: =IF(I23<>"","REORDER NOW","") -> REORDER NOW
I24: SKU57 | J24: 65 | K24: 5 | L24: 18 | M24: =IF(I24<>"","REORDER NOW","") -> REORDER NOW
B25: SHIPPING EFFICIENCY | I25: SKU58 | J25: 81 | K25: 10 | L25: 5 | M25: =IF(I25<>"","REORDER NOW","") -> REORDER NOW
B26: =Analysis!A30 -> Shipping Carrier | C26: =Analysis!B30 -> Avg Shipping Time | D26: =Analysis!C30 -> Avg Shipping Cost | I26: SKU68 | J26: 29 | K26: 0 | L26: 8 | M26: =IF(I26<>"","REORDER NOW","") -> REORDER NOW
B27: =Analysis!A31 -> Carrier B | C27: =Analysis!B31 -> 5.3023256 | D27: =Analysis!C31 -> 5.509247 | I27: SKU70 | J27: 90 | K27: 10 | L27: 12 | M27: =IF(I27<>"","REORDER NOW","") -> REORDER NOW
B28: =Analysis!A32 -> Carrier A | C28: =Analysis!B32 -> 6.1428571 | D28: =Analysis!C32 -> 5.5549225 | I28: SKU78 | J28: 50 | K28: 5 | L28: 4 | M28: =IF(I28<>"","REORDER NOW","") -> REORDER NOW
B29: =Analysis!A33 -> Carrier C | C29: =Analysis!B33 -> 6.0344828 | D29: =Analysis!C33 -> 5.5992916 | I29: SKU87 | J29: 24 | K29: 5 | L29: 7 | M29: =IF(I29<>"","REORDER NOW","") -> REORDER NOW
M30: =IF(I30<>"","REORDER NOW","")
M31: =IF(I31<>"","REORDER NOW","")
M32: =IF(I32<>"","REORDER NOW","")
M33: =IF(I33<>"","REORDER NOW","")
M34: =IF(I34<>"","REORDER NOW","")
M35: =IF(I35<>"","REORDER NOW","")

Sheet Dictionary
A1: Supply Chain Data Dictionary
A3: Column Name | B3: Data Type | C3: Business Purpose | D3: Valid Range | E3: Alert Trigger | F3: LLM Description
A4: Product type | B4: Text | C4: Categorizes products into types for sales and inventory analysis | D4: haircare | skincare | cosmetics | E4: Flag if value not in: haircare, skincare, cosmetics | F4: Use exact lowercase values: haircare, skincare, cosmetics
A5: SKU | B5: Text | C5: Uniquely identifies each product — acts as primary key | D5: SKU0 to SKU(n) — no upper limit | E5: Flag if duplicate SKU or format not matching SKU+number | F5: Primary key — use for VLOOKUP/XLOOKUP
A6: Price | B6: Decimal | C6: Unit selling price of each product | D6: > 0 | E6: Flag if Price <= 0 | F6: Unit price — use with quantity fields to calculate revenue and profit metrics
A7: Availability | B7: Integer | C7: Available quantity at the shop level for immediate sale | D7: >= 0 | E7: Flag if < 10 — adjust based on lead time | F7: Use to check current shop-level stock and identify reorder needs
A8: Number of products sold | B8: Integer | C8: Total units sold for each SKU | D8: >= 0 | E8: Flag if <= 0 or > Availability | F8: Use to analyze sales volume and demand patterns per SKU
A9: Revenue generated | B9: Decimal | C9: Total revenue earned from sales of each SKU | D9: >= 0 and >= Price | E9: Flag if Revenue < (Number of products sold * Price) | F9: Use to find total earning of business using total revenue for products sold
A10: Customer demographics | B10: Text/Categorical | C10: Identifies customer gender segment to analyze purchasing patterns | D10: Male/Female | E10: Flag if value not in: Male, Female, Non-binary, Unknown | F10: Use to segment sales by customer gender — analyze which demographics prefer which product types
A11: Stock levels | B11: Integer | C11: Total inventory stored in warehouse — backup stock available for replenishment | D11: >= 0 - 100 | E11: Flag if Stock levels <= 100 | F11: Use to monitor warehouse inventory levels — identify products needing urgent reorder
A12: Lead times | B12: Integer | C12: Number of days to receive reordered stock from supplier | D12: 1 to 30 days | E12: Flag if Lead time <= 0 or > 30 | F12: Use to plan reorders before stock runs out — combine with Stock levels to calculate reorder timing
A13: Order quantities | B13: Integer | C13: Number of units ordered per purchase order | D13: > 0 | E13: Flag if Order quantities <= 0 | F13: Use to compare with Stock levels — trigger reorder alert when stock approaches order quantity threshold
A14: Lead times | B14: Integer | C14: Number of days to receive reordered stock from supplier | D14: 2 to 30 days | E14: Flag if Lead time <= 0 or > 31 | F14: Use to plan reorders before stock runs out — combine with Stock levels to calculate reorder timing
... A27: Costs | B27: Decimal | C27: Total logistics cost incurred to move products from manufacturer to warehouse | D27: > 0 | E27: Flag if Costs > 500 (outlier) | F27: Use with Production volumes to calculate per-unit logistics cost — combine with Price to determine profit margin

Sheet Documentation
B2: Project A.1 — Supply Chain Performance Dashboard
B4: Project A.1 — Muzamil Shah | Excel Skills for Business Specialization
B6: Section 1 — Business Overview
B7: This dataset represents an online Direct-to-Consumer (D2C) business operating across multiple cities in India. The company manufactures and sells beauty products across three categories: Haircare, Skincare, and Cosmetics. When an order is placed, raw materials are sourced from suppliers, and products are manufactured in-house. Each batch undergoes quality inspection (Pass/Fail/Pending) before being transported to a central warehouse via Road, Air, Sea, or Rail. From the warehouse, customer orders are fulfilled and shipped directly to customers via third-party carriers (Carrier A, B, C).
B8: 2. PROBLEM STATEMENT — CEO QUESTIONS & ANSWERS (FROM DASHBOARD)
B9: Q1--Stock Risk: "Kaunse products khatam hone wale hain, jin ko abhi reorder karna chahiye?"
B10: Ans: 17 SKUs flagged for reorder (Dashboard → Stock Alerts table)
B12: Q2--Revenue/Demand: "Mera sabse zyada product konsa sell ho raha hai, jis pe main mazeed invest karoon?"
B13: Ans: Skincare — highest revenue ($241,628) and units sold (20,731)
B15: Q3.Supplier Quality: "Konsa manufacturer hai jiska defect ratio kam hai, aur konsa zyada?"
B16: Ans: Supplier 1 best (1.80% defect rate), Supplier 5 needs improvement (2.67%)
B18: Q4.Shipping Efficiency: "Konsa carrier sabse fast aur efficient delivery karta hai?"
... B27: 3. HOW TO NAVIGATE THIS FILE
B28: Raw Data | G28: Original dataset (100 SKUs, 24 columns) in table format (Tbl_sales).
B29: Data Dictionary | G29: Column definitions, business context, and data validation rules — written for both humans and LLMs.
B30: Analysis | G30: Calculations and formulas (SUMIF, AVERAGEIF, XLOOKUP, FILTER, UNIQUE) that answer the CEO's questions.
B31: Dashboard | G31: Visual summary with KPIs and key findings for quick decision-making.

Sheet Business Model
